fasta2csv/__init__.py
fasta2csv/converter.py
fastatocsv-0.0.4.dist-info/LICENSE
fastatocsv-0.0.4.dist-info/METADATA
fastatocsv-0.0.4.dist-info/WHEEL
fastatocsv-0.0.4.dist-info/top_level.txt
fastatocsv-0.0.4.dist-info/RECORD
